seam_carver/__init__.py
seam_carver/seam_carver.py
seam_carver/seam_carver_test.py
seam_carver-0.1.2.dist-info/DESCRIPTION.rst
seam_carver-0.1.2.dist-info/METADATA
seam_carver-0.1.2.dist-info/RECORD
seam_carver-0.1.2.dist-info/WHEEL
seam_carver-0.1.2.dist-info/metadata.json
seam_carver-0.1.2.dist-info/top_level.txt
