Metadata-Version: 2.0
Name: seam-carver
Version: 0.1.2
Summary: A small tool for retargetting images to any dimension greater or smaller
Home-page: https://github.com/dharness/seam_carving
Author: Dylan Harness
Author-email: dharness.engineer@gmail.com
License: MIT
Keywords: seam seamcarving carving liquidresizing retarget retargetting retargeting
Platform: UNKNOWN
Classifier: Development Status :: 4 - Beta
Classifier: Intended Audience :: Developers
Classifier: Programming Language :: Python :: 3
Requires-Python: >=3
Requires-Dist: Pillow (>=4.2.1)
Requires-Dist: numpy (>=1.13.1)
Requires-Dist: scipy (>=0.19.1)
